essentiax/__init__.py
essentiax/cleaning/__init__.py
essentiax/cleaning/smart_clean.py
essentiax/eda/__init__.py
essentiax/eda/smart_eda.py
essentiax/io/__init__.py
essentiax/io/smart_read.py
essentiax/summary/__init__.py
essentiax/summary/eda_pro.py
essentiax/summary/problem_card.py
essentiax/visuals/__init__.py
essentiax/visuals/smartViz.py
essentiax-0.2.5.dist-info/METADATA
essentiax-0.2.5.dist-info/WHEEL
essentiax-0.2.5.dist-info/top_level.txt
essentiax-0.2.5.dist-info/RECORD
