Metadata-Version: 2.4
Name: Essentiax
Version: 0.2.5
Summary: A next-generation Python library for smart EDA, cleaning, and interpretability in ML.
Home-page: https://github.com/ShubhamWagh/EssentiaX
Author: Shubham Wagh
Author-email: waghshubham197@gmail.com
Classifier: Programming Language :: Python :: 3
Classifier: License :: OSI Approved :: MIT License
Classifier: Operating System :: OS Independent
Classifier: Intended Audience :: Science/Research
Classifier: Intended Audience :: Developers
Classifier: Topic :: Scientific/Engineering :: Artificial Intelligence
Classifier: Topic :: Software Development :: Libraries
Requires-Python: >=3.7
Requires-Dist: pandas>=1.0
Requires-Dist: numpy>=1.20
Requires-Dist: matplotlib>=3.0
Requires-Dist: seaborn>=0.11
Requires-Dist: scikit-learn>=1.0
Requires-Dist: rich>=10.0
Requires-Dist: openpyxl>=3.0
Dynamic: author
Dynamic: author-email
Dynamic: classifier
Dynamic: description-content-type
Dynamic: home-page
Dynamic: requires-dist
Dynamic: requires-python
Dynamic: summary
